xresponse/__init__.py
xresponse/codes.py
xresponse/exception_handler.py
xresponse/response.py
xresponse-0.0.3.dist-info/METADATA
xresponse-0.0.3.dist-info/WHEEL
xresponse-0.0.3.dist-info/top_level.txt
xresponse-0.0.3.dist-info/RECORD
